[
  {
    "id": "albatross",
    "label": "CI — May 15, 2026",
    "suiteId": "suite_regression_qa",
    "envId": "qa_staging",
    "env": "QA",
    "network": "staging",
    "status": "PASS",
    "passPct": 100,
    "failures": 0,
    "duration": "0m 13s",
    "durationMs": 13620,
    "started": "2026-05-15T06:10:54.000Z",
    "build": "wtrmvj1",
    "rev": "6f974b0cc69461a4410b20177681d7a9f579f559"
  },
  {
    "id": "beacon",
    "label": "CI — May 18, 2026",
    "suiteId": "suite_regression_qa",
    "envId": "qa_prod",
    "env": "QA",
    "network": "production",
    "status": "PASS",
    "passPct": 100,
    "failures": 0,
    "duration": "0m 14s",
    "durationMs": 14200,
    "started": "2026-05-18T08:30:52.000Z",
    "build": "8z5s3b5",
    "rev": "106b30ea2ca153cbc1aa84067beb2962a74d23f1"
  },
  {
    "id": "cardinal",
    "label": "CI — May 21, 2026",
    "suiteId": "suite_regression_qa",
    "envId": "qa_staging",
    "env": "QA",
    "network": "staging",
    "status": "PASS",
    "passPct": 100,
    "failures": 0,
    "duration": "0m 17s",
    "durationMs": 17760,
    "started": "2026-05-21T07:05:54.000Z",
    "build": "55y678r",
    "rev": "43cdafd9709f5f00be5bc36957ebec0caf9a5a46"
  },
  {
    "id": "dapper",
    "label": "CI — May 24, 2026",
    "suiteId": "suite_regression_qa",
    "envId": "qa_prod",
    "env": "QA",
    "network": "production",
    "status": "FAIL",
    "passPct": 80,
    "failures": 4,
    "duration": "0m 17s",
    "durationMs": 17600,
    "started": "2026-05-24T09:45:49.000Z",
    "build": "fdsjsbr",
    "rev": "859f47b01fd25f1bde38448baae14294755ccbd2"
  },
  {
    "id": "ember",
    "label": "CI — May 27, 2026",
    "suiteId": "suite_regression_qa",
    "envId": "qa_staging",
    "env": "QA",
    "network": "staging",
    "status": "PASS",
    "passPct": 100,
    "failures": 0,
    "duration": "0m 17s",
    "durationMs": 17160,
    "started": "2026-05-27T06:00:42.000Z",
    "build": "anptogd",
    "rev": "8e87047919c9e8541702af7936e741cc4997d17d"
  },
  {
    "id": "falcon",
    "label": "CI — May 30, 2026",
    "suiteId": "suite_regression_qa",
    "envId": "qa_prod",
    "env": "QA",
    "network": "production",
    "status": "PASS",
    "passPct": 100,
    "failures": 0,
    "duration": "0m 16s",
    "durationMs": 16900,
    "started": "2026-05-30T07:30:24.000Z",
    "build": "8ez3bwe",
    "rev": "da6762cc28d5f12b4acc90d77d0dbc4e79b74ffc"
  },
  {
    "id": "granite",
    "label": "CI — Jun 2, 2026",
    "suiteId": "suite_regression_qa",
    "envId": "qa_staging",
    "env": "QA",
    "network": "staging",
    "status": "PASS",
    "passPct": 100,
    "failures": 0,
    "duration": "0m 15s",
    "durationMs": 15280,
    "started": "2026-06-02T06:15:18.000Z",
    "build": "5ki5mae",
    "rev": "5145c1121b5ed77a2972db4462addb95cc223b90"
  },
  {
    "id": "harbor",
    "label": "CI — Jun 5, 2026",
    "suiteId": "suite_regression_qa",
    "envId": "qa_prod",
    "env": "QA",
    "network": "production",
    "status": "FLAKY",
    "passPct": 95,
    "failures": 1,
    "duration": "0m 14s",
    "durationMs": 14220,
    "started": "2026-06-05T08:00:08.000Z",
    "build": "oc2xtms",
    "rev": "d57fbbfaacde45892ad5049edddd74cedb0ecc71"
  },
  {
    "id": "indigo",
    "label": "CI — Jun 8, 2026",
    "suiteId": "suite_regression_qa",
    "envId": "qa_staging",
    "env": "QA",
    "network": "staging",
    "status": "PASS",
    "passPct": 100,
    "failures": 0,
    "duration": "0m 16s",
    "durationMs": 16840,
    "started": "2026-06-08T06:30:43.000Z",
    "build": "1ok8y5j",
    "rev": "49f113b1d3e70a3fb367f139136268e5c1868310"
  },
  {
    "id": "jasper",
    "label": "CI — Jun 11, 2026",
    "suiteId": "suite_regression_qa",
    "envId": "qa_prod",
    "env": "QA",
    "network": "production",
    "status": "PASS",
    "passPct": 100,
    "failures": 0,
    "duration": "0m 15s",
    "durationMs": 15140,
    "started": "2026-06-11T07:00:37.000Z",
    "build": "dsyiqcx",
    "rev": "556b4bf31c361ca41b291f0e8366c4c9ec15b958"
  },
  {
    "id": "kestrel",
    "label": "CI — May 16, 2026",
    "suiteId": "suite_regression_uat",
    "envId": "uat_staging",
    "env": "UAT",
    "network": "staging",
    "status": "PASS",
    "passPct": 100,
    "failures": 0,
    "duration": "0m 14s",
    "durationMs": 14120,
    "started": "2026-05-16T10:00:11.000Z",
    "build": "he2m2v4",
    "rev": "424876a419386c45d314da05edc611f5835ee359"
  },
  {
    "id": "lemon",
    "label": "CI — May 19, 2026",
    "suiteId": "suite_regression_uat",
    "envId": "uat_prod",
    "env": "UAT",
    "network": "production",
    "status": "PASS",
    "passPct": 100,
    "failures": 0,
    "duration": "0m 14s",
    "durationMs": 14820,
    "started": "2026-05-19T11:30:17.000Z",
    "build": "k5kbkda",
    "rev": "f67bdef67b090f88690b6c911bf6ce100cc3310c"
  },
  {
    "id": "marble",
    "label": "CI — May 22, 2026",
    "suiteId": "suite_regression_uat",
    "envId": "uat_staging",
    "env": "UAT",
    "network": "staging",
    "status": "FAIL",
    "passPct": 85,
    "failures": 3,
    "duration": "0m 17s",
    "durationMs": 17380,
    "started": "2026-05-22T10:15:54.000Z",
    "build": "xaaqf0j",
    "rev": "35f1413d9d60f8b935bdb9100dff7e562f9ed4be"
  },
  {
    "id": "nexus",
    "label": "CI — May 25, 2026",
    "suiteId": "suite_regression_uat",
    "envId": "uat_prod",
    "env": "UAT",
    "network": "production",
    "status": "FAIL",
    "passPct": 80,
    "failures": 4,
    "duration": "0m 13s",
    "durationMs": 13960,
    "started": "2026-05-25T12:00:02.000Z",
    "build": "1oty77l",
    "rev": "30625ae1e5989c54ac3abd7422c909454c786511"
  },
  {
    "id": "ocelot",
    "label": "CI — May 28, 2026",
    "suiteId": "suite_regression_uat",
    "envId": "uat_staging",
    "env": "UAT",
    "network": "staging",
    "status": "PASS",
    "passPct": 100,
    "failures": 0,
    "duration": "0m 15s",
    "durationMs": 15800,
    "started": "2026-05-28T10:45:59.000Z",
    "build": "e6iu159",
    "rev": "2cbba9f838cbd77284c4c2b6ced6ec1d949ceca3"
  },
  {
    "id": "prism",
    "label": "CI — May 31, 2026",
    "suiteId": "suite_regression_uat",
    "envId": "uat_prod",
    "env": "UAT",
    "network": "production",
    "status": "PASS",
    "passPct": 100,
    "failures": 0,
    "duration": "0m 13s",
    "durationMs": 13200,
    "started": "2026-05-31T11:00:24.000Z",
    "build": "bujzve1",
    "rev": "dbadbc0b4dce6d8f112b721cfbd1834dab375484"
  },
  {
    "id": "quartz",
    "label": "CI — Jun 3, 2026",
    "suiteId": "suite_regression_uat",
    "envId": "uat_staging",
    "env": "UAT",
    "network": "staging",
    "status": "PASS",
    "passPct": 100,
    "failures": 0,
    "duration": "0m 17s",
    "durationMs": 17280,
    "started": "2026-06-03T10:30:24.000Z",
    "build": "aw9ybtf",
    "rev": "4d4813be2f97453ce894a9488b8377c6925459e4"
  },
  {
    "id": "ranger",
    "label": "CI — Jun 6, 2026",
    "suiteId": "suite_regression_uat",
    "envId": "uat_prod",
    "env": "UAT",
    "network": "production",
    "status": "PASS",
    "passPct": 100,
    "failures": 0,
    "duration": "0m 13s",
    "durationMs": 13840,
    "started": "2026-06-06T12:15:48.000Z",
    "build": "ck57xnh",
    "rev": "bcbb112d2ef7b8cf27d739c180438d7b92bc3a34"
  },
  {
    "id": "sierra",
    "label": "CI — Jun 9, 2026",
    "suiteId": "suite_regression_uat",
    "envId": "uat_staging",
    "env": "UAT",
    "network": "staging",
    "status": "PASS",
    "passPct": 100,
    "failures": 0,
    "duration": "0m 14s",
    "durationMs": 14360,
    "started": "2026-06-09T10:00:06.000Z",
    "build": "lg1k0ai",
    "rev": "6b9477379565c52f4143bfecce5478740280017b"
  },
  {
    "id": "tundra",
    "label": "CI — Jun 12, 2026",
    "suiteId": "suite_regression_uat",
    "envId": "uat_prod",
    "env": "UAT",
    "network": "production",
    "status": "FLAKY",
    "passPct": 95,
    "failures": 1,
    "duration": "0m 13s",
    "durationMs": 13380,
    "started": "2026-06-12T11:45:05.000Z",
    "build": "e7ig9gq",
    "rev": "38747d0e2eeedbf818545391440d9f85a16dcb96"
  },
  {
    "id": "ultron",
    "label": "CI — May 17, 2026",
    "suiteId": "suite_nightly_prod",
    "envId": "prod_staging",
    "env": "PROD",
    "network": "staging",
    "status": "FLAKY",
    "passPct": 95,
    "failures": 1,
    "duration": "0m 14s",
    "durationMs": 14740,
    "started": "2026-05-17T02:00:38.000Z",
    "build": "jzhdyts",
    "rev": "c7b1eb9a47bd475a420def69b76ca2d925819bfd"
  },
  {
    "id": "vantage",
    "label": "CI — May 20, 2026",
    "suiteId": "suite_nightly_prod",
    "envId": "prod_prod",
    "env": "PROD",
    "network": "production",
    "status": "PASS",
    "passPct": 100,
    "failures": 0,
    "duration": "0m 13s",
    "durationMs": 13200,
    "started": "2026-05-20T02:30:06.000Z",
    "build": "in8teya",
    "rev": "66a13630a06da1eae25d394da2972d91fdc3ac78"
  },
  {
    "id": "willow",
    "label": "CI — May 23, 2026",
    "suiteId": "suite_nightly_prod",
    "envId": "prod_staging",
    "env": "PROD",
    "network": "staging",
    "status": "FAIL",
    "passPct": 85,
    "failures": 3,
    "duration": "0m 13s",
    "durationMs": 13960,
    "started": "2026-05-23T02:15:11.000Z",
    "build": "ulf3wsv",
    "rev": "2e01ac056529c30c041896ff4e5efd842dc0d2fb"
  },
  {
    "id": "xenon",
    "label": "CI — May 26, 2026",
    "suiteId": "suite_nightly_prod",
    "envId": "prod_prod",
    "env": "PROD",
    "network": "production",
    "status": "FAIL",
    "passPct": 80,
    "failures": 4,
    "duration": "0m 16s",
    "durationMs": 16220,
    "started": "2026-05-26T02:00:31.000Z",
    "build": "3xtcdvu",
    "rev": "c542a8a86f5f0e27245d7100760be86cbaa6c5c5"
  },
  {
    "id": "yellow",
    "label": "CI — May 29, 2026",
    "suiteId": "suite_nightly_prod",
    "envId": "prod_staging",
    "env": "PROD",
    "network": "staging",
    "status": "PASS",
    "passPct": 100,
    "failures": 0,
    "duration": "0m 14s",
    "durationMs": 14340,
    "started": "2026-05-29T02:45:48.000Z",
    "build": "rse5g9y",
    "rev": "aa746b36803b65bcd544878b993ab24c2c56276b"
  },
  {
    "id": "zephyr",
    "label": "CI — Jun 1, 2026",
    "suiteId": "suite_nightly_prod",
    "envId": "prod_prod",
    "env": "PROD",
    "network": "production",
    "status": "PASS",
    "passPct": 100,
    "failures": 0,
    "duration": "0m 17s",
    "durationMs": 17080,
    "started": "2026-06-01T02:00:16.000Z",
    "build": "10sklk1",
    "rev": "335547974a263753f68df8e15aba1df96caee005"
  },
  {
    "id": "amber",
    "label": "CI — Jun 4, 2026",
    "suiteId": "suite_nightly_prod",
    "envId": "prod_staging",
    "env": "PROD",
    "network": "staging",
    "status": "PASS",
    "passPct": 100,
    "failures": 0,
    "duration": "0m 17s",
    "durationMs": 17360,
    "started": "2026-06-04T02:30:14.000Z",
    "build": "8gfyeuu",
    "rev": "2e2c2162b8f78bce91b6627cd5a449d4af922825"
  },
  {
    "id": "blaze",
    "label": "CI — Jun 7, 2026",
    "suiteId": "suite_nightly_prod",
    "envId": "prod_prod",
    "env": "PROD",
    "network": "production",
    "status": "PASS",
    "passPct": 100,
    "failures": 0,
    "duration": "0m 13s",
    "durationMs": 13940,
    "started": "2026-06-07T02:15:31.000Z",
    "build": "ygdbvpn",
    "rev": "fd9ae1d4bb343e8430134d2027cb533faf88d77a"
  },
  {
    "id": "cobalt",
    "label": "CI — Jun 10, 2026",
    "suiteId": "suite_nightly_prod",
    "envId": "prod_staging",
    "env": "PROD",
    "network": "staging",
    "status": "PASS",
    "passPct": 100,
    "failures": 0,
    "duration": "0m 16s",
    "durationMs": 16140,
    "started": "2026-06-10T02:00:03.000Z",
    "build": "4li2zc4",
    "rev": "e569e03f01a5a2bd2d49a7f30a5a1bfbef5a7cae"
  },
  {
    "id": "delta",
    "label": "CI — Jun 13, 2026",
    "suiteId": "suite_nightly_prod",
    "envId": "prod_prod",
    "env": "PROD",
    "network": "production",
    "status": "PASS",
    "passPct": 100,
    "failures": 0,
    "duration": "0m 13s",
    "durationMs": 13980,
    "started": "2026-06-13T02:30:30.000Z",
    "build": "zm3ja9b",
    "rev": "773cb77cb400f30a656284fb51897511a6bf20d7"
  }
]